[
    {
      "Author": "DarkmodeLeyla",
      "Name": "TimelineAnimator",
      "InternalName": "TimelineAnimator",
      "AssemblyVersion": "1.0.0",
      "TestingAssemblyVersion": "1.0.0",
      "Description": "A simple keyframe editor to create and play back animations using Ktisis. Use /animator to open the plugin window.",
      "ApplicableVersion": "any",
      "RepoUrl": "https://github.com/NanaKhide/TimelineAnimator",
      "Tags": ["posing","animation","timeline"],
      "DownloadLinkInstall": "https://github.com/NanaKhide/TimelineAnimator/releases/download/v1.0.0/TimelineAnimator.zip",
      "DownloadLinkTesting": "https://github.com/NanaKhide/TimelineAnimator/releases/download/v1.0.0/TimelineAnimator.zip",
      "DownloadLinkUpdate": "https://github.com/NanaKhide/TimelineAnimator/releases/download/v1.0.0/TimelineAnimator.zip",
      "DalamudApiLevel": 13,
      "LoadRequiredState": 0,
      "LoadSync": false,
      "CanUnloadAsync": false,
      "LoadPriority": 0,
      "Punchline": "A keyframe animator for in-game animation.",
      "AcceptsFeedback": false
    }
  ]
